{
      "auto_generated_queries": {
            "topic": 13,
            "query": [
                  {
                        "proportion": 0.12564102564102564,
                        "terms": [
                              "conclusion"
                        ]
                  },
                  {
                        "proportion": 0.22564102564102564,
                        "terms": [
                              "conclusion",
                              "s",
                              "8",
                              "amdt",
                              "argument"
                        ]
                  },
                  {
                        "proportion": 0.32564102564102565,
                        "terms": [
                              "conclusion",
                              "s",
                              "8",
                              "amdt",
                              "argument",
                              "breyer",
                              "capi",
                              "case",
                              "circum"
                        ]
                  },
                  {
                        "proportion": 0.4256410256410257,
                        "terms": [
                              "conclusion",
                              "s",
                              "8",
                              "amdt",
                              "argument",
                              "breyer",
                              "capi",
                              "case",
                              "circum",
                              "coming",
                              "consistent",
                              "constitution",
                              "court"
                        ]
                  },
                  {
                        "proportion": 0.5256410256410257,
                        "terms": [
                              "conclusion",
                              "s",
                              "8",
                              "amdt",
                              "argument",
                              "breyer",
                              "capi",
                              "case",
                              "circum",
                              "coming",
                              "consistent",
                              "constitution",
                              "court",
                              "cruel",
                              "currently",
                              "dissenting",
                              "explored"
                        ]
                  },
                  {
                        "proportion": 0.6256410256410256,
                        "terms": [
                              "conclusion",
                              "s",
                              "8",
                              "amdt",
                              "argument",
                              "breyer",
                              "capi",
                              "case",
                              "circum",
                              "coming",
                              "consistent",
                              "constitution",
                              "court",
                              "cruel",
                              "currently",
                              "dissenting",
                              "explored",
                              "facts",
                              "have",
                              "hear",
                              "i"
                        ]
                  },
                  {
                        "proportion": 0.7256410256410256,
                        "terms": [
                              "conclusion",
                              "s",
                              "8",
                              "amdt",
                              "argument",
                              "breyer",
                              "capi",
                              "case",
                              "circum",
                              "coming",
                              "consistent",
                              "constitution",
                              "court",
                              "cruel",
                              "currently",
                              "dissenting",
                              "explored",
                              "facts",
                              "have",
                              "hear",
                              "i",
                              "ishment",
                              "j",
                              "matters",
                              "more"
                        ]
                  },
                  {
                        "proportion": 0.8256410256410256,
                        "terms": [
                              "conclusion",
                              "s",
                              "8",
                              "amdt",
                              "argument",
                              "breyer",
                              "capi",
                              "case",
                              "circum",
                              "coming",
                              "consistent",
                              "constitution",
                              "court",
                              "cruel",
                              "currently",
                              "dissenting",
                              "explored",
                              "facts",
                              "have",
                              "hear",
                              "i",
                              "ishment",
                              "j",
                              "matters",
                              "more",
                              "practiced",
                              "previously",
                              "prohibition",
                              "pun"
                        ]
                  },
                  {
                        "proportion": 0.9256410256410256,
                        "terms": [
                              "conclusion",
                              "s",
                              "8",
                              "amdt",
                              "argument",
                              "breyer",
                              "capi",
                              "case",
                              "circum",
                              "coming",
                              "consistent",
                              "constitution",
                              "court",
                              "cruel",
                              "currently",
                              "dissenting",
                              "explored",
                              "facts",
                              "have",
                              "hear",
                              "i",
                              "ishment",
                              "j",
                              "matters",
                              "more",
                              "practiced",
                              "previously",
                              "prohibition",
                              "pun",
                              "punishment",
                              "reinforce",
                              "see",
                              "should"
                        ]
                  },
                  {
                        "proportion": 1,
                        "terms": [
                              "conclusion",
                              "s",
                              "8",
                              "amdt",
                              "argument",
                              "breyer",
                              "capi",
                              "case",
                              "circum",
                              "coming",
                              "consistent",
                              "constitution",
                              "court",
                              "cruel",
                              "currently",
                              "dissenting",
                              "explored",
                              "facts",
                              "have",
                              "hear",
                              "i",
                              "ishment",
                              "j",
                              "matters",
                              "more",
                              "practiced",
                              "previously",
                              "prohibition",
                              "pun",
                              "punishment",
                              "reinforce",
                              "see",
                              "should",
                              "smith",
                              "stances",
                              "systematically",
                              "tal"
                        ]
                  },
                  {
                        "proportion": 1,
                        "terms": [
                              "conclusion",
                              "s",
                              "8",
                              "amdt",
                              "argument",
                              "breyer",
                              "capi",
                              "case",
                              "circum",
                              "coming",
                              "consistent",
                              "constitution",
                              "court",
                              "cruel",
                              "currently",
                              "dissenting",
                              "explored",
                              "facts",
                              "have",
                              "hear",
                              "i",
                              "ishment",
                              "j",
                              "matters",
                              "more",
                              "practiced",
                              "previously",
                              "prohibition",
                              "pun",
                              "punishment",
                              "reinforce",
                              "see",
                              "should",
                              "smith",
                              "stances",
                              "systematically",
                              "tal",
                              "unusual",
                              "whether"
                        ]
                  }
            ]
      }
}